dataset_convert_toolkit/__init__.py
dataset_convert_toolkit/dataset_convert_tool.py
dataset_convert_toolkit/json_file_tool.py
dataset_convert_toolkit/ua_detrac_convert_tool.py
dataset_convert_toolkit/detect_tool_yolo/__init__.py
dataset_convert_toolkit/detect_tool_yolo/cocojson2yolo.py
dataset_convert_toolkit/detect_tool_yolo/labelmejson2yolo.py
dataset_convert_toolkit/detect_tool_yolo/rectvocxml2yolo.py
dataset_convert_toolkit/ua_detrac_tool/__init__.py
dataset_convert_toolkit/ua_detrac_tool/ua_detrac_convert_voc.py
dataset_convert_toolkit/ua_detrac_tool/ua_detrac_convert_yolo.py
dataset_convert_toolkit/utils/__init__.py
dataset_convert_toolkit/utils/file.py
dataset_convert_toolkit-0.0.2.dist-info/LICENSE
dataset_convert_toolkit-0.0.2.dist-info/METADATA
dataset_convert_toolkit-0.0.2.dist-info/WHEEL
dataset_convert_toolkit-0.0.2.dist-info/top_level.txt
dataset_convert_toolkit-0.0.2.dist-info/RECORD
