Metadata-Version: 2.1
Name: dataset_convert_toolkit
Version: 0.0.2
Summary: 一个简单的深度学习数据集转换工具
Home-page: https://github.com/porterpan/dataset_convert_toolkit
Author: porter pan
Author-email: porter.pan@outlook.com
Classifier: Programming Language :: Python :: 3
Classifier: License :: OSI Approved :: Apache Software License
Classifier: Operating System :: OS Independent
Requires-Python: >=3.6
License-File: LICENSE
Requires-Dist: argparse
Requires-Dist: numpy <=1.24.2
Requires-Dist: opencv-python <=4.9.0.80
Requires-Dist: PyYAML <=6.0.1
Requires-Dist: tqdm <=4.66.4
Requires-Dist: jsons <=1.6.3
